aiida_mlip-0.3.0.dist-info/METADATA
aiida_mlip-0.3.0.dist-info/WHEEL
aiida_mlip-0.3.0.dist-info/entry_points.txt
aiida_mlip-0.3.0.dist-info/licenses/LICENSE
aiida_mlip/__init__.py
aiida_mlip/calculations/__init__.py
aiida_mlip/calculations/base.py
aiida_mlip/calculations/descriptors.py
aiida_mlip/calculations/geomopt.py
aiida_mlip/calculations/md.py
aiida_mlip/calculations/singlepoint.py
aiida_mlip/calculations/train.py
aiida_mlip/data/__init__.py
aiida_mlip/data/config.py
aiida_mlip/data/model.py
aiida_mlip/helpers/__init__.py
aiida_mlip/helpers/converters.py
aiida_mlip/helpers/help_load.py
aiida_mlip/parsers/__init__.py
aiida_mlip/parsers/base_parser.py
aiida_mlip/parsers/descriptors_parser.py
aiida_mlip/parsers/md_parser.py
aiida_mlip/parsers/opt_parser.py
aiida_mlip/parsers/sp_parser.py
aiida_mlip/parsers/train_parser.py
aiida_mlip/workflows/__init__.py
aiida_mlip/workflows/ht_workgraph.py
aiida_mlip-0.3.0.dist-info/RECORD
