Metadata-Version: 2.1
Name: aiida-mlip
Version: 0.3.0
Summary: Machine learning interatomic potentials AiiDA plugin
Keywords: aiida,plugin
Author: Federica Zanca, Elliott Kasoar, Jacob Wilkins, Alin M. Elena
Classifier: Programming Language :: Python
Classifier: Intended Audience :: Science/Research
Classifier: License :: OSI Approved :: BSD License
Classifier: Natural Language :: English
Classifier: Development Status :: 5 - Production/Stable
Classifier: Framework :: AiiDA
Project-URL: repository, https://github.com/stfc/aiida-mlip/
Project-URL: documentation, https://stfc.github.io/aiida-mlip/
Project-URL: source, https://github.com/aiidateam/aiida-mlip
Requires-Python: >=3.10
Requires-Dist: aiida-core<3,>=2.6.3
Requires-Dist: ase<4.0,>=3.24
Requires-Dist: voluptuous<1,>=0.15.2
Requires-Dist: janus-core<0.8,>=0.7.5
Requires-Dist: aiida-workgraph<0.6,>=0.5.3
Provides-Extra: mace
Requires-Dist: janus-core[mace]; extra == "mace"
